{"commitInfo":{"timestamp":1759887045795,"operation":"WRITE","operationParameters":{"mode":"Overwrite","partitionBy":"[]"},"readVersion":1,"isolationLevel":"Serializable","isBlindAppend":false,"operationMetrics":{"numFiles":"8","numOutputRows":"100","numOutputBytes":"20622"},"engineInfo":"Apache-Spark/3.5.7 Delta-Lake/3.2.0","txnId":"995f724b-53d6-4371-b94f-6c01d56b13e5"}}
{"add":{"path":"part-00000-65b7f74b-4dbf-413a-be0b-c52e2a08eb1e-c000.snappy.parquet","partitionValues":{},"size":2558,"modificationTime":1759887044032,"dataChange":true,"stats":"{\"numRecords\":12,\"minValues\":{\"close\":140.25,\"high\":144.0,\"low\":139.5,\"open\":141.75,\"timestamp\":\"2025-09-22\",\"volume\":5559529,\"ingestion_time\":\"2025-10-07T21:30:42.082-04:00\"},\"maxValues\":{\"close\":164.5,\"high\":169.69,\"low\":162.81,\"open\":166.55,\"timestamp\":\"2025-10-07\",\"volume\":15740154,\"ingestion_time\":\"2025-10-07T21:30:42.082-04:00\"},\"nullCount\":{\"close\":0,\"high\":0,\"low\":0,\"open\":0,\"timestamp\":0,\"volume\":0,\"ingestion_time\":0}}"}}
{"add":{"path":"part-00001-82a3825a-4072-4427-b9aa-f67947890258-c000.snappy.parquet","partitionValues":{},"size":2563,"modificationTime":1759887044030,"dataChange":true,"stats":"{\"numRecords\":12,\"minValues\":{\"close\":142.2,\"high\":144.62,\"low\":140.0732,\"open\":140.905,\"timestamp\":\"2025-09-04\",\"volume\":4291166,\"ingestion_time\":\"2025-10-07T21:30:42.082-04:00\"},\"maxValues\":{\"close\":153.3,\"high\":155.13,\"low\":151.75,\"open\":151.96,\"timestamp\":\"2025-09-19\",\"volume\":8812925,\"ingestion_time\":\"2025-10-07T21:30:42.082-04:00\"},\"nullCount\":{\"close\":0,\"high\":0,\"low\":0,\"open\":0,\"timestamp\":0,\"volume\":0,\"ingestion_time\":0}}"}}
{"add":{"path":"part-00002-4061c8a4-e52f-46c6-b4b1-c08b80ade5ab-c000.snappy.parquet","partitionValues":{},"size":2551,"modificationTime":1759887044030,"dataChange":true,"stats":"{\"numRecords\":12,\"minValues\":{\"close\":136.68,\"high\":137.96,\"low\":133.4,\"open\":136.26,\"timestamp\":\"2025-08-18\",\"volume\":3491922,\"ingestion_time\":\"2025-10-07T21:30:42.082-04:00\"},\"maxValues\":{\"close\":143.11,\"high\":144.41,\"low\":140.59,\"open\":143.0,\"timestamp\":\"2025-09-03\",\"volume\":7649750,\"ingestion_time\":\"2025-10-07T21:30:42.082-04:00\"},\"nullCount\":{\"close\":0,\"high\":0,\"low\":0,\"open\":0,\"timestamp\":0,\"volume\":0,\"ingestion_time\":0}}"}}
{"add":{"path":"part-00003-fc0081ef-009a-492e-abe0-9297b4cb6f08-c000.snappy.parquet","partitionValues":{},"size":2562,"modificationTime":1759887044030,"dataChange":true,"stats":"{\"numRecords\":12,\"minValues\":{\"close\":118.6,\"high\":120.19,\"low\":115.95,\"open\":118.05,\"timestamp\":\"2025-07-31\",\"volume\":6660684,\"ingestion_time\":\"2025-10-07T21:30:42.082-04:00\"},\"maxValues\":{\"close\":154.9,\"high\":156.85,\"low\":148.39,\"open\":154.46,\"timestamp\":\"2025-08-15\",\"volume\":38572096,\"ingestion_time\":\"2025-10-07T21:30:42.082-04:00\"},\"nullCount\":{\"close\":0,\"high\":0,\"low\":0,\"open\":0,\"timestamp\":0,\"volume\":0,\"ingestion_time\":0}}"}}
{"add":{"path":"part-00004-21949bd9-181c-4107-bd21-8de4bd2eb23e-c000.snappy.parquet","partitionValues":{},"size":2550,"modificationTime":1759887044030,"dataChange":true,"stats":"{\"numRecords\":12,\"minValues\":{\"close\":115.05,\"high\":118.65,\"low\":112.59,\"open\":114.29,\"timestamp\":\"2025-07-15\",\"volume\":4313070,\"ingestion_time\":\"2025-10-07T21:30:42.082-04:00\"},\"maxValues\":{\"close\":128.43,\"high\":129.29,\"low\":126.6,\"open\":127.83,\"timestamp\":\"2025-07-30\",\"volume\":13380625,\"ingestion_time\":\"2025-10-07T21:30:42.082-04:00\"},\"nullCount\":{\"close\":0,\"high\":0,\"low\":0,\"open\":0,\"timestamp\":0,\"volume\":0,\"ingestion_time\":0}}"}}
{"add":{"path":"part-00005-e1436f6f-9c99-4522-bc60-f3b4d9244298-c000.snappy.parquet","partitionValues":{},"size":2561,"modificationTime":1759887044030,"dataChange":true,"stats":"{\"numRecords\":12,\"minValues\":{\"close\":112.11,\"high\":113.76,\"low\":108.33,\"open\":111.8,\"timestamp\":\"2025-06-26\",\"volume\":3773554,\"ingestion_time\":\"2025-10-07T21:30:42.082-04:00\"},\"maxValues\":{\"close\":116.74,\"high\":118.46,\"low\":114.97,\"open\":117.414,\"timestamp\":\"2025-07-14\",\"volume\":11368234,\"ingestion_time\":\"2025-10-07T21:30:42.082-04:00\"},\"nullCount\":{\"close\":0,\"high\":0,\"low\":0,\"open\":0,\"timestamp\":0,\"volume\":0,\"ingestion_time\":0}}"}}
{"add":{"path":"part-00006-afc78f70-09f9-4bea-90c7-f573bc52a924-c000.snappy.parquet","partitionValues":{},"size":2569,"modificationTime":1759887044031,"dataChange":true,"stats":"{\"numRecords\":12,\"minValues\":{\"close\":105.34,\"high\":107.01,\"low\":103.9117,\"open\":105.53,\"timestamp\":\"2025-06-09\",\"volume\":4910867,\"ingestion_time\":\"2025-10-07T21:30:42.082-04:00\"},\"maxValues\":{\"close\":114.42,\"high\":117.3599,\"low\":112.86,\"open\":114.28,\"timestamp\":\"2025-06-25\",\"volume\":14078071,\"ingestion_time\":\"2025-10-07T21:30:42.082-04:00\"},\"nullCount\":{\"close\":0,\"high\":0,\"low\":0,\"open\":0,\"timestamp\":0,\"volume\":0,\"ingestion_time\":0}}"}}
{"add":{"path":"part-00007-250facf1-846e-4119-9bfb-eef2c4623c9b-c000.snappy.parquet","partitionValues":{},"size":2708,"modificationTime":1759887044030,"dataChange":true,"stats":"{\"numRecords\":16,\"minValues\":{\"close\":101.51,\"high\":102.96,\"low\":100.31,\"open\":100.81,\"timestamp\":\"2025-05-15\",\"volume\":5341427,\"ingestion_time\":\"2025-10-07T21:30:42.082-04:00\"},\"maxValues\":{\"close\":111.41,\"high\":112.38,\"low\":109.7974,\"open\":111.56,\"timestamp\":\"2025-06-06\",\"volume\":96081410,\"ingestion_time\":\"2025-10-07T21:30:42.082-04:00\"},\"nullCount\":{\"close\":0,\"high\":0,\"low\":0,\"open\":0,\"timestamp\":0,\"volume\":0,\"ingestion_time\":0}}"}}
{"remove":{"path":"part-00002-b9872db9-51dc-4b04-b730-120e04b7f5ad-c000.snappy.parquet","deletionTimestamp":1759887045638,"dataChange":true,"extendedFileMetadata":true,"partitionValues":{},"size":2551}}
{"remove":{"path":"part-00006-25c561d9-4e14-4d66-8cc9-fa5bee1743b4-c000.snappy.parquet","deletionTimestamp":1759887045638,"dataChange":true,"extendedFileMetadata":true,"partitionValues":{},"size":2569}}
{"remove":{"path":"part-00000-6bc70cdd-3d5a-4612-8f23-5d637060cfac-c000.snappy.parquet","deletionTimestamp":1759887045638,"dataChange":true,"extendedFileMetadata":true,"partitionValues":{},"size":2558}}
{"remove":{"path":"part-00004-cf00c064-6e32-41b5-a3bf-e2ee6ce01c6b-c000.snappy.parquet","deletionTimestamp":1759887045638,"dataChange":true,"extendedFileMetadata":true,"partitionValues":{},"size":2550}}
{"remove":{"path":"part-00003-ce38d2e9-bf44-448f-ac29-c638d44b4642-c000.snappy.parquet","deletionTimestamp":1759887045638,"dataChange":true,"extendedFileMetadata":true,"partitionValues":{},"size":2562}}
{"remove":{"path":"part-00007-a830fb75-8093-4abf-a84b-27204509155f-c000.snappy.parquet","deletionTimestamp":1759887045638,"dataChange":true,"extendedFileMetadata":true,"partitionValues":{},"size":2708}}
{"remove":{"path":"part-00005-c7d233cb-f532-4d87-8266-50deb7a87e60-c000.snappy.parquet","deletionTimestamp":1759887045638,"dataChange":true,"extendedFileMetadata":true,"partitionValues":{},"size":2561}}
{"remove":{"path":"part-00001-f12b3d89-e7d3-461f-95a4-36d50089bd8f-c000.snappy.parquet","deletionTimestamp":1759887045638,"dataChange":true,"extendedFileMetadata":true,"partitionValues":{},"size":2563}}
